pipeline_materials_file/__init__.py
pipeline_materials_file-1.0.dist-info/LICENSE
pipeline_materials_file-1.0.dist-info/METADATA
pipeline_materials_file-1.0.dist-info/WHEEL
pipeline_materials_file-1.0.dist-info/top_level.txt
pipeline_materials_file-1.0.dist-info/RECORD
