Metadata-Version: 2.1
Name: pipeline-materials-file
Version: 1.0
Summary: Pipeline materials file for static integrity calculation
Home-page: https://github.com/vb64/pipeline.materials.file
Author: Vitaly Bogomolov
Author-email: mail@vitaly-bogomolov.ru
Project-URL: Bug Tracker, https://github.com/vb64/pipeline.materials.file/issues
Classifier: Programming Language :: Python :: 3
Classifier: License :: OSI Approved :: MIT License
Classifier: Operating System :: OS Independent
Requires-Python: >=3.6
License-File: LICENSE
Requires-Dist: pipeline-material
Requires-Dist: pipeline-csv
